rendercv/__init__.py
rendercv/__main__.py
rendercv/cli/__init__.py
rendercv/cli/app.py
rendercv/cli/copy_templates.py
rendercv/cli/create_theme_command/__init__.py
rendercv/cli/create_theme_command/create_init_file_for_theme.py
rendercv/cli/create_theme_command/create_theme_command.py
rendercv/cli/entry_point.py
rendercv/cli/error_handler.py
rendercv/cli/new_command/__init__.py
rendercv/cli/new_command/new_command.py
rendercv/cli/new_command/print_welcome.py
rendercv/cli/render_command/__init__.py
rendercv/cli/render_command/parse_override_arguments.py
rendercv/cli/render_command/progress_panel.py
rendercv/cli/render_command/render_command.py
rendercv/cli/render_command/run_rendercv.py
rendercv/cli/render_command/watcher.py
rendercv/exception.py
rendercv/renderer/__init__.py
rendercv/renderer/html.py
rendercv/renderer/markdown.py
rendercv/renderer/path_resolver.py
rendercv/renderer/pdf_png.py
rendercv/renderer/templater/__init__.py
rendercv/renderer/templater/connections.py
rendercv/renderer/templater/date.py
rendercv/renderer/templater/entry_templates_from_input.py
rendercv/renderer/templater/footer_and_top_note.py
rendercv/renderer/templater/markdown_parser.py
rendercv/renderer/templater/model_processor.py
rendercv/renderer/templater/string_processor.py
rendercv/renderer/templater/templater.py
rendercv/renderer/templater/templates/html/Full.html
rendercv/renderer/templater/templates/markdown/Header.j2.md
rendercv/renderer/templater/templates/markdown/SectionBeginning.j2.md
rendercv/renderer/templater/templates/markdown/SectionEnding.j2.md
rendercv/renderer/templater/templates/markdown/entries/BulletEntry.j2.md
rendercv/renderer/templater/templates/markdown/entries/EducationEntry.j2.md
rendercv/renderer/templater/templates/markdown/entries/ExperienceEntry.j2.md
rendercv/renderer/templater/templates/markdown/entries/NormalEntry.j2.md
rendercv/renderer/templater/templates/markdown/entries/NumberedEntry.j2.md
rendercv-2.5.dist-info/WHEEL
rendercv-2.5.dist-info/entry_points.txt
rendercv-2.5.dist-info/METADATA
rendercv-2.5.dist-info/RECORD
