Metadata-Version: 2.4
Name: rendercv
Version: 2.5
Summary: Typst-based CV/resume generator
Author: Sina Atalay
Author-email: Sina Atalay <dev@atalay.biz>
License-Expression: MIT
Classifier: Intended Audience :: Science/Research
Classifier: Intended Audience :: Education
Classifier: Topic :: Text Processing :: Markup
Classifier: Topic :: Printing
Classifier: Development Status :: 5 - Production/Stable
Classifier: Programming Language :: Python :: 3.10
Classifier: Programming Language :: Python :: 3.11
Classifier: Programming Language :: Python :: 3.12
Classifier: Programming Language :: Python :: 3.13
Classifier: Programming Language :: Python :: 3.14
Classifier: License :: OSI Approved :: MIT License
Classifier: Operating System :: OS Independent
Requires-Dist: jinja2>=3.1.6
Requires-Dist: phonenumbers>=9.0.19
Requires-Dist: pydantic[email]>=2.10.6
Requires-Dist: pydantic-extra-types>=2.10.6
Requires-Dist: ruamel-yaml>=0.18.10
Requires-Dist: packaging>=25.0
Requires-Dist: typer>=0.20.0 ; extra == 'full'
Requires-Dist: markdown>=3.10 ; extra == 'full'
Requires-Dist: watchdog>=6.0.0 ; extra == 'full'
Requires-Dist: typst>=0.14.4 ; extra == 'full'
Requires-Dist: rendercv-fonts>=0.5.1 ; extra == 'full'
Requires-Python: >=3.12
Project-URL: Changelog, https://docs.rendercv.com/changelog
Project-URL: Documentation, https://docs.rendercv.com
Project-URL: Source, https://github.com/rendercv/rendercv
Project-URL: Web App, https://rendercv.com
Provides-Extra: full
